<?xml version='1.0' encoding='utf-8'?>
<Patch>
  <Operation Class="PatchOperationAdd">
    <xpath>/Defs/FactionDef[@Name="TribeBase"]/pawnGroupMakers</xpath>
    <value>
      <li>
        <kindDef>Trader</kindDef>
        <traders>
          <Tribal_Trader>1</Tribal_Trader>
        </traders>
        <carriers>
          <Muffalo>6</Muffalo>
          <Dromedary>5</Dromedary>
          <Alpaca>2.5</Alpaca>
          <Elephant>2</Elephant>
        </carriers>
        <guards>
          <Tribal_Warrior>7</Tribal_Warrior>
          <Tribal_Archer>10</Tribal_Archer>
          <Tribal_Hunter>10</Tribal_Hunter>
          <Tribal_HeavyArcher>10</Tribal_HeavyArcher>
          <Tribal_Berserker>7</Tribal_Berserker>
          <BetaBear_Tribal_Warrior>7.00</BetaBear_Tribal_Warrior>
          <BetaCamel_Tribal_Warrior>7.00</BetaCamel_Tribal_Warrior>
          <BetaCroc_Tribal_Warrior>4.90</BetaCroc_Tribal_Warrior>
          <BetaElephant_Tribal_Warrior>1.75</BetaElephant_Tribal_Warrior>
          <BetaElk_Female_Tribal_Warrior>0.35</BetaElk_Female_Tribal_Warrior>
          <BetaElk_Male_Tribal_Warrior>0.35</BetaElk_Male_Tribal_Warrior>
          <BetaFox_Tribal_Warrior>7.00</BetaFox_Tribal_Warrior>
          <BetaGazelle_Tribal_Warrior>7.00</BetaGazelle_Tribal_Warrior>
          <BetaHog_Tribal_Warrior>7.00</BetaHog_Tribal_Warrior>
          <BetaLynx_Tribal_Warrior>7.00</BetaLynx_Tribal_Warrior>
          <BetaRaccoon_Tribal_Warrior>7.00</BetaRaccoon_Tribal_Warrior>
          <BetaWolf_Tribal_Warrior>7.00</BetaWolf_Tribal_Warrior>
          <BetaBear_Tribal_Archer>10.00</BetaBear_Tribal_Archer>
          <BetaCamel_Tribal_Archer>10.00</BetaCamel_Tribal_Archer>
          <BetaCroc_Tribal_Archer>7.00</BetaCroc_Tribal_Archer>
          <BetaElephant_Tribal_Archer>2.50</BetaElephant_Tribal_Archer>
          <BetaElk_Female_Tribal_Archer>0.50</BetaElk_Female_Tribal_Archer>
          <BetaElk_Male_Tribal_Archer>0.50</BetaElk_Male_Tribal_Archer>
          <BetaFox_Tribal_Archer>10.00</BetaFox_Tribal_Archer>
          <BetaGazelle_Tribal_Archer>10.00</BetaGazelle_Tribal_Archer>
          <BetaHog_Tribal_Archer>10.00</BetaHog_Tribal_Archer>
          <BetaLynx_Tribal_Archer>10.00</BetaLynx_Tribal_Archer>
          <BetaRaccoon_Tribal_Archer>10.00</BetaRaccoon_Tribal_Archer>
          <BetaWolf_Tribal_Archer>10.00</BetaWolf_Tribal_Archer>
          <BetaBear_Tribal_Hunter>10.00</BetaBear_Tribal_Hunter>
          <BetaCamel_Tribal_Hunter>10.00</BetaCamel_Tribal_Hunter>
          <BetaCroc_Tribal_Hunter>7.00</BetaCroc_Tribal_Hunter>
          <BetaElephant_Tribal_Hunter>2.50</BetaElephant_Tribal_Hunter>
          <BetaElk_Female_Tribal_Hunter>0.50</BetaElk_Female_Tribal_Hunter>
          <BetaElk_Male_Tribal_Hunter>0.50</BetaElk_Male_Tribal_Hunter>
          <BetaFox_Tribal_Hunter>10.00</BetaFox_Tribal_Hunter>
          <BetaGazelle_Tribal_Hunter>10.00</BetaGazelle_Tribal_Hunter>
          <BetaHog_Tribal_Hunter>10.00</BetaHog_Tribal_Hunter>
          <BetaLynx_Tribal_Hunter>10.00</BetaLynx_Tribal_Hunter>
          <BetaRaccoon_Tribal_Hunter>10.00</BetaRaccoon_Tribal_Hunter>
          <BetaWolf_Tribal_Hunter>10.00</BetaWolf_Tribal_Hunter>
          <BetaBear_Tribal_HeavyArcher>10.00</BetaBear_Tribal_HeavyArcher>
          <BetaCamel_Tribal_HeavyArcher>10.00</BetaCamel_Tribal_HeavyArcher>
          <BetaCroc_Tribal_HeavyArcher>7.00</BetaCroc_Tribal_HeavyArcher>
          <BetaElephant_Tribal_HeavyArcher>2.50</BetaElephant_Tribal_HeavyArcher>
          <BetaElk_Female_Tribal_HeavyArcher>0.50</BetaElk_Female_Tribal_HeavyArcher>
          <BetaElk_Male_Tribal_HeavyArcher>0.50</BetaElk_Male_Tribal_HeavyArcher>
          <BetaFox_Tribal_HeavyArcher>10.00</BetaFox_Tribal_HeavyArcher>
          <BetaGazelle_Tribal_HeavyArcher>10.00</BetaGazelle_Tribal_HeavyArcher>
          <BetaHog_Tribal_HeavyArcher>10.00</BetaHog_Tribal_HeavyArcher>
          <BetaLynx_Tribal_HeavyArcher>10.00</BetaLynx_Tribal_HeavyArcher>
          <BetaRaccoon_Tribal_HeavyArcher>10.00</BetaRaccoon_Tribal_HeavyArcher>
          <BetaWolf_Tribal_HeavyArcher>10.00</BetaWolf_Tribal_HeavyArcher>
          <BetaBear_Tribal_Berserker>7.00</BetaBear_Tribal_Berserker>
          <BetaCamel_Tribal_Berserker>7.00</BetaCamel_Tribal_Berserker>
          <BetaCroc_Tribal_Berserker>4.90</BetaCroc_Tribal_Berserker>
          <BetaElephant_Tribal_Berserker>1.75</BetaElephant_Tribal_Berserker>
          <BetaElk_Female_Tribal_Berserker>0.35</BetaElk_Female_Tribal_Berserker>
          <BetaElk_Male_Tribal_Berserker>0.35</BetaElk_Male_Tribal_Berserker>
          <BetaFox_Tribal_Berserker>7.00</BetaFox_Tribal_Berserker>
          <BetaGazelle_Tribal_Berserker>7.00</BetaGazelle_Tribal_Berserker>
          <BetaHog_Tribal_Berserker>7.00</BetaHog_Tribal_Berserker>
          <BetaLynx_Tribal_Berserker>7.00</BetaLynx_Tribal_Berserker>
          <BetaRaccoon_Tribal_Berserker>7.00</BetaRaccoon_Tribal_Berserker>
          <BetaWolf_Tribal_Berserker>7.00</BetaWolf_Tribal_Berserker>
        </guards>
      </li>
      <li>
        <kindDef>Trader</kindDef>
        <traders>
          <Tribal_Trader>1</Tribal_Trader>
        </traders>
        <carriers>
          <Muffalo>6</Muffalo>
          <Dromedary>5</Dromedary>
          <Alpaca>2.5</Alpaca>
          <Elephant>2</Elephant>
        </carriers>
        <guards>
          <BetaBear_Tribal_Warrior>7.00</BetaBear_Tribal_Warrior>
          <BetaBear_Tribal_Archer>10.00</BetaBear_Tribal_Archer>
          <BetaBear_Tribal_Hunter>10.00</BetaBear_Tribal_Hunter>
          <BetaBear_Tribal_HeavyArcher>10.00</BetaBear_Tribal_HeavyArcher>
          <BetaBear_Tribal_Berserker>7.00</BetaBear_Tribal_Berserker>
          <BetaCamel_Tribal_Warrior>7.00</BetaCamel_Tribal_Warrior>
          <BetaCamel_Tribal_Archer>10.00</BetaCamel_Tribal_Archer>
          <BetaCamel_Tribal_Hunter>10.00</BetaCamel_Tribal_Hunter>
          <BetaCamel_Tribal_HeavyArcher>10.00</BetaCamel_Tribal_HeavyArcher>
          <BetaCamel_Tribal_Berserker>7.00</BetaCamel_Tribal_Berserker>
          <BetaCroc_Tribal_Warrior>4.90</BetaCroc_Tribal_Warrior>
          <BetaCroc_Tribal_Archer>7.00</BetaCroc_Tribal_Archer>
          <BetaCroc_Tribal_Hunter>7.00</BetaCroc_Tribal_Hunter>
          <BetaCroc_Tribal_HeavyArcher>7.00</BetaCroc_Tribal_HeavyArcher>
          <BetaCroc_Tribal_Berserker>4.90</BetaCroc_Tribal_Berserker>
          <BetaElephant_Tribal_Warrior>1.75</BetaElephant_Tribal_Warrior>
          <BetaElephant_Tribal_Archer>2.50</BetaElephant_Tribal_Archer>
          <BetaElephant_Tribal_Hunter>2.50</BetaElephant_Tribal_Hunter>
          <BetaElephant_Tribal_HeavyArcher>2.50</BetaElephant_Tribal_HeavyArcher>
          <BetaElephant_Tribal_Berserker>1.75</BetaElephant_Tribal_Berserker>
          <BetaElk_Female_Tribal_Warrior>0.35</BetaElk_Female_Tribal_Warrior>
          <BetaElk_Male_Tribal_Warrior>0.35</BetaElk_Male_Tribal_Warrior>
          <BetaElk_Female_Tribal_Archer>0.50</BetaElk_Female_Tribal_Archer>
          <BetaElk_Male_Tribal_Archer>0.50</BetaElk_Male_Tribal_Archer>
          <BetaElk_Female_Tribal_Hunter>0.50</BetaElk_Female_Tribal_Hunter>
          <BetaElk_Male_Tribal_Hunter>0.50</BetaElk_Male_Tribal_Hunter>
          <BetaElk_Female_Tribal_HeavyArcher>0.50</BetaElk_Female_Tribal_HeavyArcher>
          <BetaElk_Male_Tribal_HeavyArcher>0.50</BetaElk_Male_Tribal_HeavyArcher>
          <BetaElk_Female_Tribal_Berserker>0.35</BetaElk_Female_Tribal_Berserker>
          <BetaElk_Male_Tribal_Berserker>0.35</BetaElk_Male_Tribal_Berserker>
          <BetaFox_Tribal_Warrior>7.00</BetaFox_Tribal_Warrior>
          <BetaFox_Tribal_Archer>10.00</BetaFox_Tribal_Archer>
          <BetaFox_Tribal_Hunter>10.00</BetaFox_Tribal_Hunter>
          <BetaFox_Tribal_HeavyArcher>10.00</BetaFox_Tribal_HeavyArcher>
          <BetaFox_Tribal_Berserker>7.00</BetaFox_Tribal_Berserker>
          <BetaGazelle_Tribal_Warrior>7.00</BetaGazelle_Tribal_Warrior>
          <BetaGazelle_Tribal_Archer>10.00</BetaGazelle_Tribal_Archer>
          <BetaGazelle_Tribal_Hunter>10.00</BetaGazelle_Tribal_Hunter>
          <BetaGazelle_Tribal_HeavyArcher>10.00</BetaGazelle_Tribal_HeavyArcher>
          <BetaGazelle_Tribal_Berserker>7.00</BetaGazelle_Tribal_Berserker>
          <BetaHog_Tribal_Warrior>7.00</BetaHog_Tribal_Warrior>
          <BetaHog_Tribal_Archer>10.00</BetaHog_Tribal_Archer>
          <BetaHog_Tribal_Hunter>10.00</BetaHog_Tribal_Hunter>
          <BetaHog_Tribal_HeavyArcher>10.00</BetaHog_Tribal_HeavyArcher>
          <BetaHog_Tribal_Berserker>7.00</BetaHog_Tribal_Berserker>
          <BetaLynx_Tribal_Warrior>7.00</BetaLynx_Tribal_Warrior>
          <BetaLynx_Tribal_Archer>10.00</BetaLynx_Tribal_Archer>
          <BetaLynx_Tribal_Hunter>10.00</BetaLynx_Tribal_Hunter>
          <BetaLynx_Tribal_HeavyArcher>10.00</BetaLynx_Tribal_HeavyArcher>
          <BetaLynx_Tribal_Berserker>7.00</BetaLynx_Tribal_Berserker>
          <BetaRaccoon_Tribal_Warrior>7.00</BetaRaccoon_Tribal_Warrior>
          <BetaRaccoon_Tribal_Archer>10.00</BetaRaccoon_Tribal_Archer>
          <BetaRaccoon_Tribal_Hunter>10.00</BetaRaccoon_Tribal_Hunter>
          <BetaRaccoon_Tribal_HeavyArcher>10.00</BetaRaccoon_Tribal_HeavyArcher>
          <BetaRaccoon_Tribal_Berserker>7.00</BetaRaccoon_Tribal_Berserker>
          <BetaWolf_Tribal_Warrior>7.00</BetaWolf_Tribal_Warrior>
          <BetaWolf_Tribal_Archer>10.00</BetaWolf_Tribal_Archer>
          <BetaWolf_Tribal_Hunter>10.00</BetaWolf_Tribal_Hunter>
          <BetaWolf_Tribal_HeavyArcher>10.00</BetaWolf_Tribal_HeavyArcher>
          <BetaWolf_Tribal_Berserker>7.00</BetaWolf_Tribal_Berserker>
        </guards>
      </li>
      <li>
        <kindDef>Trader</kindDef>
        <traders>
          <Tribal_Trader>1</Tribal_Trader>
        </traders>
        <carriers>
          <Muffalo>6</Muffalo>
          <Dromedary>5</Dromedary>
          <Alpaca>2.5</Alpaca>
          <Elephant>2</Elephant>
        </carriers>
        <guards>
          <BetaBear_Tribal_Warrior>7.00</BetaBear_Tribal_Warrior>
          <BetaBear_Tribal_Archer>10.00</BetaBear_Tribal_Archer>
          <BetaBear_Tribal_Hunter>10.00</BetaBear_Tribal_Hunter>
          <BetaBear_Tribal_HeavyArcher>10.00</BetaBear_Tribal_HeavyArcher>
          <BetaBear_Tribal_Berserker>7.00</BetaBear_Tribal_Berserker>
        </guards>
      </li>
      <li>
        <kindDef>Trader</kindDef>
        <traders>
          <Tribal_Trader>1</Tribal_Trader>
        </traders>
        <carriers>
          <Muffalo>6</Muffalo>
          <Dromedary>5</Dromedary>
          <Alpaca>2.5</Alpaca>
          <Elephant>2</Elephant>
        </carriers>
        <guards>
          <BetaCamel_Tribal_Warrior>7.00</BetaCamel_Tribal_Warrior>
          <BetaCamel_Tribal_Archer>10.00</BetaCamel_Tribal_Archer>
          <BetaCamel_Tribal_Hunter>10.00</BetaCamel_Tribal_Hunter>
          <BetaCamel_Tribal_HeavyArcher>10.00</BetaCamel_Tribal_HeavyArcher>
          <BetaCamel_Tribal_Berserker>7.00</BetaCamel_Tribal_Berserker>
        </guards>
      </li>
      <li>
        <kindDef>Trader</kindDef>
        <traders>
          <Tribal_Trader>1</Tribal_Trader>
        </traders>
        <carriers>
          <Muffalo>6</Muffalo>
          <Dromedary>5</Dromedary>
          <Alpaca>2.5</Alpaca>
          <Elephant>2</Elephant>
        </carriers>
        <guards>
          <BetaCroc_Tribal_Warrior>4.90</BetaCroc_Tribal_Warrior>
          <BetaCroc_Tribal_Archer>7.00</BetaCroc_Tribal_Archer>
          <BetaCroc_Tribal_Hunter>7.00</BetaCroc_Tribal_Hunter>
          <BetaCroc_Tribal_HeavyArcher>7.00</BetaCroc_Tribal_HeavyArcher>
          <BetaCroc_Tribal_Berserker>4.90</BetaCroc_Tribal_Berserker>
        </guards>
      </li>
      <li>
        <kindDef>Trader</kindDef>
        <traders>
          <Tribal_Trader>1</Tribal_Trader>
        </traders>
        <carriers>
          <Muffalo>6</Muffalo>
          <Dromedary>5</Dromedary>
          <Alpaca>2.5</Alpaca>
          <Elephant>2</Elephant>
        </carriers>
        <guards>
          <BetaElephant_Tribal_Warrior>1.75</BetaElephant_Tribal_Warrior>
          <BetaElephant_Tribal_Archer>2.50</BetaElephant_Tribal_Archer>
          <BetaElephant_Tribal_Hunter>2.50</BetaElephant_Tribal_Hunter>
          <BetaElephant_Tribal_HeavyArcher>2.50</BetaElephant_Tribal_HeavyArcher>
          <BetaElephant_Tribal_Berserker>1.75</BetaElephant_Tribal_Berserker>
        </guards>
      </li>
      <li>
        <kindDef>Trader</kindDef>
        <traders>
          <Tribal_Trader>1</Tribal_Trader>
        </traders>
        <carriers>
          <Muffalo>6</Muffalo>
          <Dromedary>5</Dromedary>
          <Alpaca>2.5</Alpaca>
          <Elephant>2</Elephant>
        </carriers>
        <guards>
          <BetaElk_Female_Tribal_Warrior>0.35</BetaElk_Female_Tribal_Warrior>
          <BetaElk_Male_Tribal_Warrior>0.35</BetaElk_Male_Tribal_Warrior>
          <BetaElk_Female_Tribal_Archer>0.50</BetaElk_Female_Tribal_Archer>
          <BetaElk_Male_Tribal_Archer>0.50</BetaElk_Male_Tribal_Archer>
          <BetaElk_Female_Tribal_Hunter>0.50</BetaElk_Female_Tribal_Hunter>
          <BetaElk_Male_Tribal_Hunter>0.50</BetaElk_Male_Tribal_Hunter>
          <BetaElk_Female_Tribal_HeavyArcher>0.50</BetaElk_Female_Tribal_HeavyArcher>
          <BetaElk_Male_Tribal_HeavyArcher>0.50</BetaElk_Male_Tribal_HeavyArcher>
          <BetaElk_Female_Tribal_Berserker>0.35</BetaElk_Female_Tribal_Berserker>
          <BetaElk_Male_Tribal_Berserker>0.35</BetaElk_Male_Tribal_Berserker>
        </guards>
      </li>
      <li>
        <kindDef>Trader</kindDef>
        <traders>
          <Tribal_Trader>1</Tribal_Trader>
        </traders>
        <carriers>
          <Muffalo>6</Muffalo>
          <Dromedary>5</Dromedary>
          <Alpaca>2.5</Alpaca>
          <Elephant>2</Elephant>
        </carriers>
        <guards>
          <BetaFox_Tribal_Warrior>7.00</BetaFox_Tribal_Warrior>
          <BetaFox_Tribal_Archer>10.00</BetaFox_Tribal_Archer>
          <BetaFox_Tribal_Hunter>10.00</BetaFox_Tribal_Hunter>
          <BetaFox_Tribal_HeavyArcher>10.00</BetaFox_Tribal_HeavyArcher>
          <BetaFox_Tribal_Berserker>7.00</BetaFox_Tribal_Berserker>
        </guards>
      </li>
      <li>
        <kindDef>Trader</kindDef>
        <traders>
          <Tribal_Trader>1</Tribal_Trader>
        </traders>
        <carriers>
          <Muffalo>6</Muffalo>
          <Dromedary>5</Dromedary>
          <Alpaca>2.5</Alpaca>
          <Elephant>2</Elephant>
        </carriers>
        <guards>
          <BetaGazelle_Tribal_Warrior>7.00</BetaGazelle_Tribal_Warrior>
          <BetaGazelle_Tribal_Archer>10.00</BetaGazelle_Tribal_Archer>
          <BetaGazelle_Tribal_Hunter>10.00</BetaGazelle_Tribal_Hunter>
          <BetaGazelle_Tribal_HeavyArcher>10.00</BetaGazelle_Tribal_HeavyArcher>
          <BetaGazelle_Tribal_Berserker>7.00</BetaGazelle_Tribal_Berserker>
        </guards>
      </li>
      <li>
        <kindDef>Trader</kindDef>
        <traders>
          <Tribal_Trader>1</Tribal_Trader>
        </traders>
        <carriers>
          <Muffalo>6</Muffalo>
          <Dromedary>5</Dromedary>
          <Alpaca>2.5</Alpaca>
          <Elephant>2</Elephant>
        </carriers>
        <guards>
          <BetaHog_Tribal_Warrior>7.00</BetaHog_Tribal_Warrior>
          <BetaHog_Tribal_Archer>10.00</BetaHog_Tribal_Archer>
          <BetaHog_Tribal_Hunter>10.00</BetaHog_Tribal_Hunter>
          <BetaHog_Tribal_HeavyArcher>10.00</BetaHog_Tribal_HeavyArcher>
          <BetaHog_Tribal_Berserker>7.00</BetaHog_Tribal_Berserker>
        </guards>
      </li>
      <li>
        <kindDef>Trader</kindDef>
        <traders>
          <Tribal_Trader>1</Tribal_Trader>
        </traders>
        <carriers>
          <Muffalo>6</Muffalo>
          <Dromedary>5</Dromedary>
          <Alpaca>2.5</Alpaca>
          <Elephant>2</Elephant>
        </carriers>
        <guards>
          <BetaLynx_Tribal_Warrior>7.00</BetaLynx_Tribal_Warrior>
          <BetaLynx_Tribal_Archer>10.00</BetaLynx_Tribal_Archer>
          <BetaLynx_Tribal_Hunter>10.00</BetaLynx_Tribal_Hunter>
          <BetaLynx_Tribal_HeavyArcher>10.00</BetaLynx_Tribal_HeavyArcher>
          <BetaLynx_Tribal_Berserker>7.00</BetaLynx_Tribal_Berserker>
        </guards>
      </li>
      <li>
        <kindDef>Trader</kindDef>
        <traders>
          <Tribal_Trader>1</Tribal_Trader>
        </traders>
        <carriers>
          <Muffalo>6</Muffalo>
          <Dromedary>5</Dromedary>
          <Alpaca>2.5</Alpaca>
          <Elephant>2</Elephant>
        </carriers>
        <guards>
          <BetaRaccoon_Tribal_Warrior>7.00</BetaRaccoon_Tribal_Warrior>
          <BetaRaccoon_Tribal_Archer>10.00</BetaRaccoon_Tribal_Archer>
          <BetaRaccoon_Tribal_Hunter>10.00</BetaRaccoon_Tribal_Hunter>
          <BetaRaccoon_Tribal_HeavyArcher>10.00</BetaRaccoon_Tribal_HeavyArcher>
          <BetaRaccoon_Tribal_Berserker>7.00</BetaRaccoon_Tribal_Berserker>
        </guards>
      </li>
      <li>
        <kindDef>Trader</kindDef>
        <traders>
          <Tribal_Trader>1</Tribal_Trader>
        </traders>
        <carriers>
          <Muffalo>6</Muffalo>
          <Dromedary>5</Dromedary>
          <Alpaca>2.5</Alpaca>
          <Elephant>2</Elephant>
        </carriers>
        <guards>
          <BetaWolf_Tribal_Warrior>7.00</BetaWolf_Tribal_Warrior>
          <BetaWolf_Tribal_Archer>10.00</BetaWolf_Tribal_Archer>
          <BetaWolf_Tribal_Hunter>10.00</BetaWolf_Tribal_Hunter>
          <BetaWolf_Tribal_HeavyArcher>10.00</BetaWolf_Tribal_HeavyArcher>
          <BetaWolf_Tribal_Berserker>7.00</BetaWolf_Tribal_Berserker>
        </guards>
      </li>
    </value>
  </Operation>
</Patch>